listwalker/__init__.py
listwalker-1.1.dist-info/LICENSE
listwalker-1.1.dist-info/METADATA
listwalker-1.1.dist-info/WHEEL
listwalker-1.1.dist-info/top_level.txt
listwalker-1.1.dist-info/RECORD
