Metadata-Version: 2.1
Name: listwalker
Version: 1.1
Summary: A tool for traversing multi-dimensional lists.
Home-page: https://github.com/NadieFiind/listwalker
Author: Nadie Fiind
Author-email: nadiefiind@gmail.com
Classifier: Programming Language :: Python :: 3
Classifier: License :: OSI Approved :: MIT License
Classifier: Operating System :: OS Independent
Requires-Python: >=3.6
License-File: LICENSE
